resource/ros2systemd
ros2systemd/__init__.py
ros2systemd/api/__init__.py
ros2systemd/api/systemd_manager.py
ros2systemd/command/__init__.py
ros2systemd/command/systemd.py
ros2systemd/templates/__init__.py
ros2systemd/verb/__init__.py
ros2systemd/verb/create.py
ros2systemd/verb/diagnose.py
ros2systemd/verb/disable.py
ros2systemd/verb/enable.py
ros2systemd/verb/launch.py
ros2systemd/verb/list.py
ros2systemd/verb/logs.py
ros2systemd/verb/remove.py
ros2systemd/verb/restart.py
ros2systemd/verb/run.py
ros2systemd/verb/start.py
ros2systemd/verb/status.py
ros2systemd/verb/stop.py
ros2systemd/verb/template.py
ros2systemd-0.5.1.data/data/share/ament_index/resource_index/packages/ros2systemd
ros2systemd-0.5.1.data/data/share/ros2systemd/package.xml
ros2systemd-0.5.1.dist-info/licenses/LICENSE
ros2systemd-0.5.1.dist-info/METADATA
ros2systemd-0.5.1.dist-info/WHEEL
ros2systemd-0.5.1.dist-info/entry_points.txt
ros2systemd-0.5.1.dist-info/top_level.txt
ros2systemd-0.5.1.dist-info/zip-safe
ros2systemd-0.5.1.dist-info/RECORD
