Metadata-Version: 2.4
Name: ros2systemd
Version: 0.5.1
Summary: ROS2 command extension for managing launches and nodes as systemd services
Author: Jerry Lin
Author-email: Jerry Lin <jerry73204@gmail.com>
Maintainer: Jerry Lin
Maintainer-email: Jerry Lin <jerry73204@gmail.com>
License: Apache-2.0
Project-URL: Homepage, https://github.com/jerry73204/ros2systemd
Project-URL: Bug Reports, https://github.com/jerry73204/ros2systemd/issues
Project-URL: Source, https://github.com/jerry73204/ros2systemd
Project-URL: Documentation, https://github.com/jerry73204/ros2systemd#readme
Keywords: ros2,systemd,service,daemon,node,launch
Classifier: Development Status :: 4 - Beta
Classifier: Intended Audience :: Developers
Classifier: License :: OSI Approved :: Apache Software License
Classifier: Operating System :: POSIX :: Linux
Classifier: Programming Language :: Python :: 3
Classifier: Programming Language :: Python :: 3.8
Classifier: Programming Language :: Python :: 3.9
Classifier: Programming Language :: Python :: 3.10
Classifier: Programming Language :: Python :: 3.11
Requires-Python: >=3.8
License-File: LICENSE
Requires-Dist: setuptools
Provides-Extra: dev
Requires-Dist: pytest; extra == "dev"
Requires-Dist: pytest-cov; extra == "dev"
Dynamic: author
Dynamic: license-file
Dynamic: maintainer
